JavaNioJianmingJiaochengV10/README.md
JavaNioJianmingJiaochengV10/__init__.py
JavaNioJianmingJiaochengV10/__main__.py
JavaNioJianmingJiaochengV10/file.epub
JavaNioJianmingJiaochengV10/index.html
JavaNioJianmingJiaochengV10/css/__init__.py
JavaNioJianmingJiaochengV10/css/annotations.css
JavaNioJianmingJiaochengV10/css/main.css
JavaNioJianmingJiaochengV10/css/normalize.css
JavaNioJianmingJiaochengV10/css/popup.css
JavaNioJianmingJiaochengV10/font/__init__.py
JavaNioJianmingJiaochengV10/font/fontello.eot
JavaNioJianmingJiaochengV10/font/fontello.svg
JavaNioJianmingJiaochengV10/font/fontello.ttf
JavaNioJianmingJiaochengV10/font/fontello.woff
JavaNioJianmingJiaochengV10/img/__init__.py
JavaNioJianmingJiaochengV10/img/annotator-glyph-sprite.png
JavaNioJianmingJiaochengV10/img/annotator-icon-sprite.png
JavaNioJianmingJiaochengV10/img/apple-touch-icon.png
JavaNioJianmingJiaochengV10/img/cancelfullscreen.png
JavaNioJianmingJiaochengV10/img/close.png
JavaNioJianmingJiaochengV10/img/fullscreen.png
JavaNioJianmingJiaochengV10/img/loader.gif
JavaNioJianmingJiaochengV10/img/menu-icon.png
JavaNioJianmingJiaochengV10/img/save.png
JavaNioJianmingJiaochengV10/img/saved.png
JavaNioJianmingJiaochengV10/img/settings-s.png
JavaNioJianmingJiaochengV10/img/settings.png
JavaNioJianmingJiaochengV10/img/star.png
JavaNioJianmingJiaochengV10/js/__init__.py
JavaNioJianmingJiaochengV10/js/epub.js
JavaNioJianmingJiaochengV10/js/epub.min.js
JavaNioJianmingJiaochengV10/js/epub.min.map
JavaNioJianmingJiaochengV10/js/hooks.min.js
JavaNioJianmingJiaochengV10/js/hooks.min.map
JavaNioJianmingJiaochengV10/js/reader.js
JavaNioJianmingJiaochengV10/js/reader.js.map
JavaNioJianmingJiaochengV10/js/reader.min.js
JavaNioJianmingJiaochengV10/js/reader.min.map
JavaNioJianmingJiaochengV10/js/hooks/__init__.py
JavaNioJianmingJiaochengV10/js/hooks/extensions/__init__.py
JavaNioJianmingJiaochengV10/js/hooks/extensions/highlight.js
JavaNioJianmingJiaochengV10/js/libs/__init__.py
java_nio_jianming_jiaocheng_v1_0-2024.3.2.0.dist-info/METADATA
java_nio_jianming_jiaocheng_v1_0-2024.3.2.0.dist-info/WHEEL
java_nio_jianming_jiaocheng_v1_0-2024.3.2.0.dist-info/entry_points.txt
java_nio_jianming_jiaocheng_v1_0-2024.3.2.0.dist-info/top_level.txt
java_nio_jianming_jiaocheng_v1_0-2024.3.2.0.dist-info/RECORD
